[
  {
    "id": "choco_bar",
    "name_kr": "초코바",
    "grade": "D",
    "desc": "건물 어딘가에 방치된 간식. 유통기한은 이미 지났지만 먹을 만하다.",
    "effects": [
      {
        "stat_key": "max_hp",
        "label_kr": "최대 체력",
        "value": 3.0,
        "mode": "add"
      }
    ],
    "sources": [
      "KIOSK",
      "TREASURE"
    ]
  },
  {
    "id": "worn_boots",
    "name_kr": "낡은 장화",
    "grade": "D",
    "desc": "누군가 급히 도망치며 버린 장화. 밑창이 닳았지만 없는 것보단 낫다.",
    "effects": [
      {
        "stat_key": "move_speed",
        "label_kr": "이동속도",
        "value": 1.0,
        "mode": "add"
      }
    ],
    "sources": [
      "KIOSK",
      "TREASURE"
    ]
  },
  {
    "id": "work_gloves",
    "name_kr": "작업용 장갑",
    "grade": "D",
    "desc": "KRONOS 건설 현장 표준 지급품. 어디서나 구할 수 있다.",
    "effects": [
      {
        "stat_key": "attack_speed",
        "label_kr": "공격속도",
        "value": 1.0,
        "mode": "add"
      }
    ],
    "sources": [
      "KIOSK",
      "TREASURE"
    ]
  },
  {
    "id": "beginners_dumbbell",
    "name_kr": "초보자 덤벨",
    "grade": "D",
    "desc": "낡은 피트니스 센터 장비. 무기로 쓸 생각은 없었지만 효과는 있다.",
    "effects": [
      {
        "stat_key": "attack_power_flat",
        "label_kr": "공격력 (고정)",
        "value": 1.0,
        "mode": "add"
      }
    ],
    "sources": [
      "KIOSK"
    ]
  },
  {
    "id": "energy_jelly",
    "name_kr": "젤리",
    "grade": "D",
    "desc": "KRONOS 배급 비상 식품. 맛은 없지만 회복에는 도움이 된다.",
    "effects": [
      {
        "stat_key": "hp_regen",
        "label_kr": "체력 재생",
        "value": 2.0,
        "mode": "add"
      }
    ],
    "sources": [
      "KIOSK",
      "TREASURE"
    ]
  },
  {
    "id": "gold_coin",
    "name_kr": "금화",
    "grade": "D",
    "desc": "재화를 모을수록 이자가 붙는다. 출처는 불명.",
    "effects": [
      {
        "stat_key": "interest_bonus",
        "label_kr": "이자 보너스",
        "value": 2.0,
        "mode": "add"
      }
    ],
    "sources": [
      "KIOSK",
      "TREASURE"
    ]
  },
  {
    "id": "dust_mask",
    "name_kr": "먼지 마스크",
    "grade": "D",
    "desc": "건설 현장용 분진 마스크. 벽 안의 질소도 어느 정도 걸러준다.",
    "effects": [
      {
        "stat_key": "oxygen_drain_rate",
        "label_kr": "산소 소모 속도",
        "value": -0.1,
        "mode": "multiply"
      }
    ],
    "sources": [
      "KIOSK",
      "TREASURE"
    ]
  },
  {
    "id": "emergency_ration",
    "name_kr": "비상 식량",
    "grade": "D",
    "desc": "KRONOS가 각 층 비상 창고에 비치해둔 비상 식량. 봉인이 그대로다.",
    "effects": [
      {
        "stat_key": "max_hp",
        "label_kr": "최대 체력",
        "value": 5.0,
        "mode": "add"
      }
    ],
    "sources": [
      "TREASURE"
    ]
  },
  {
    "id": "rusty_hammer",
    "name_kr": "녹슨 망치",
    "grade": "D",
    "desc": "건설 현장 유물. 무겁지만 한 방이 묵직하다.",
    "effects": [
      {
        "stat_key": "attack_power_flat",
        "label_kr": "공격력 (고정)",
        "value": 2.0,
        "mode": "add"
      },
      {
        "stat_key": "attack_speed",
        "label_kr": "공격속도",
        "value": -1.0,
        "mode": "add"
      }
    ],
    "sources": [
      "TREASURE"
    ]
  },
  {
    "id": "hard_hat",
    "name_kr": "안전모",
    "grade": "D",
    "desc": "KRONOS 표준 안전 장비. 위에서 뭔가 떨어진다는 걸 설계자도 알았던 모양이다.",
    "effects": [
      {
        "stat_key": "max_hp",
        "label_kr": "최대 체력",
        "value": 4.0,
        "mode": "add"
      },
      {
        "stat_key": "fall_dmg_reduction",
        "label_kr": "낙하물 피해 감소",
        "value": 0.1,
        "mode": "add"
      }
    ],
    "sources": [
      "KIOSK",
      "TREASURE"
    ]
  },
  {
    "id": "scrap_circuit",
    "name_kr": "폐회로 부품",
    "grade": "D",
    "desc": "AEGIS 로봇의 부서진 회로 기판. KIOSK에서 현금화 가치가 있다.",
    "effects": [
      {
        "stat_key": "gold_gain_mult",
        "label_kr": "재화 획득 배율",
        "value": 0.05,
        "mode": "add"
      }
    ],
    "sources": [
      "TREASURE"
    ]
  },
  {
    "id": "emergency_bandage",
    "name_kr": "응급 붕대",
    "grade": "D",
    "desc": "각 층 응급 처치함에 남아있던 붕대. 비상 전력 덕에 멸균 상태가 유지됐다.",
    "effects": [
      {
        "stat_key": "hp_regen",
        "label_kr": "체력 재생",
        "value": 3.0,
        "mode": "add"
      }
    ],
    "sources": [
      "KIOSK",
      "TREASURE"
    ]
  },
  {
    "id": "steroid",
    "name_kr": "스테로이드",
    "grade": "C",
    "desc": "KRONOS 물자 창고에서 발견된 약물. 부작용은 감수해야 한다.",
    "effects": [
      {
        "stat_key": "attack_speed",
        "label_kr": "공격속도",
        "value": 5.0,
        "mode": "add"
      },
      {
        "stat_key": "max_hp",
        "label_kr": "최대 체력",
        "value": -5.0,
        "mode": "add"
      }
    ],
    "sources": [
      "KIOSK",
      "TREASURE"
    ]
  },
  {
    "id": "skates",
    "name_kr": "스케이트",
    "grade": "C",
    "desc": "파괴된 레크리에이션 구역에서 발견. 빠르지만 도약이 어렵다.",
    "effects": [
      {
        "stat_key": "move_speed",
        "label_kr": "이동속도",
        "value": 5.0,
        "mode": "add"
      },
      {
        "stat_key": "jump_force",
        "label_kr": "점프력",
        "value": -5.0,
        "mode": "add"
      }
    ],
    "sources": [
      "KIOSK",
      "TREASURE"
    ]
  },
  {
    "id": "suspicious_drug",
    "name_kr": "수상한 약물",
    "grade": "C",
    "desc": "라벨이 벗겨진 바이알. KRONOS 실험실에서 흘러나온 것으로 추정된다.",
    "effects": [
      {
        "stat_key": "attack_power_flat",
        "label_kr": "공격력 (고정)",
        "value": 5.0,
        "mode": "add"
      },
      {
        "stat_key": "max_hp",
        "label_kr": "최대 체력",
        "value": -5.0,
        "mode": "add"
      }
    ],
    "sources": [
      "TREASURE"
    ]
  },
  {
    "id": "heavy_armor",
    "name_kr": "무거운 갑옷",
    "grade": "C",
    "desc": "KRONOS 경비원 지급 방호복. 방어력은 탁월하나 기동성을 희생한다.",
    "effects": [
      {
        "stat_key": "max_hp",
        "label_kr": "최대 체력",
        "value": 10.0,
        "mode": "add"
      },
      {
        "stat_key": "move_speed",
        "label_kr": "이동속도",
        "value": -3.0,
        "mode": "add"
      },
      {
        "stat_key": "jump_force",
        "label_kr": "점프력",
        "value": -3.0,
        "mode": "add"
      }
    ],
    "sources": [
      "KIOSK",
      "TREASURE"
    ]
  },
  {
    "id": "kronos_ballistic_vest",
    "name_kr": "KRONOS 방탄복",
    "grade": "C",
    "desc": "이중 구조 내부에서 발견된 KRONOS 지급 장비. 일반 경비원용보다 등급이 높다.",
    "effects": [
      {
        "stat_key": "max_hp",
        "label_kr": "최대 체력",
        "value": 12.0,
        "mode": "add"
      },
      {
        "stat_key": "move_speed",
        "label_kr": "이동속도",
        "value": -2.0,
        "mode": "add"
      }
    ],
    "sources": [
      "TREASURE"
    ]
  },
  {
    "id": "oxygen_tank",
    "name_kr": "산소 탱크",
    "grade": "C",
    "desc": "질소 봉인 구역 전용 소형 산소 탱크. 벽 안에서 버틸 수 있는 시간이 크게 늘어난다.",
    "effects": [
      {
        "stat_key": "oxygen_drain_rate",
        "label_kr": "산소 소모 속도",
        "value": -0.4,
        "mode": "multiply"
      }
    ],
    "sources": [
      "KIOSK",
      "TREASURE"
    ]
  },
  {
    "id": "shock_boots",
    "name_kr": "충격 흡수 부츠",
    "grade": "C",
    "desc": "KRONOS 건설 현장 안전화 상위 모델. 잔해가 쏟아지는 환경을 고려해 설계됐다.",
    "effects": [
      {
        "stat_key": "move_speed",
        "label_kr": "이동속도",
        "value": 3.0,
        "mode": "add"
      },
      {
        "stat_key": "fall_dmg_reduction",
        "label_kr": "낙하물 피해 감소",
        "value": 0.2,
        "mode": "add"
      }
    ],
    "sources": [
      "KIOSK"
    ]
  },
  {
    "id": "aegis_jammer",
    "name_kr": "AEGIS 전원 재머",
    "grade": "C",
    "desc": "AEGIS 유지보수팀이 쓰던 장비. 전력 신호를 교란해 로봇을 더 오래 멈출 수 있다.",
    "effects": [],
    "sources": [
      "TREASURE",
      "ROBOT_DROP"
    ]
  },
  {
    "id": "load_sensor_spoofer",
    "name_kr": "하중 감지기 스푸퍼",
    "grade": "C",
    "desc": "하중 센서에 허위 신호를 보내는 장치. KRONOS 보안팀이 테스트용으로 만든 것으로 추정.",
    "effects": [
      {
        "stat_key": "weight_limit_mult",
        "label_kr": "무게 한계 배율",
        "value": 0.1,
        "mode": "add"
      }
    ],
    "sources": [
      "TREASURE"
    ]
  },
  {
    "id": "nano_syringe",
    "name_kr": "나노 주사기",
    "grade": "C",
    "desc": "이중 구조 내부에서 발견된 의료용 나노머신 주사기. 회복이 빠르지만 장기 투여는 위험하다.",
    "effects": [
      {
        "stat_key": "hp_regen",
        "label_kr": "체력 재생",
        "value": 8.0,
        "mode": "add"
      },
      {
        "stat_key": "max_hp",
        "label_kr": "최대 체력",
        "value": -5.0,
        "mode": "add"
      }
    ],
    "sources": [
      "TREASURE"
    ]
  },
  {
    "id": "inspectors_pass",
    "name_kr": "점검관 출입증",
    "grade": "C",
    "desc": "전직 KRONOS 점검관이 사용하던 구형 출입증. 손상된 보안 서버 덕에 아직 일부 권한이 살아있다.",
    "effects": [
      {
        "stat_key": "kiosk_price_mult",
        "label_kr": "KIOSK 가격 배율",
        "value": -0.15,
        "mode": "add"
      }
    ],
    "sources": [
      "TREASURE"
    ]
  },
  {
    "id": "kronos_prototype_blade",
    "name_kr": "KRONOS 프로토타입 검",
    "grade": "B",
    "desc": "KRONOS 무기 개발팀이 제작한 프로토타입. 실전 배치 전 창고에 봉인됐다.",
    "effects": [
      {
        "stat_key": "attack_power_flat",
        "label_kr": "공격력 (고정)",
        "value": 12.0,
        "mode": "add"
      }
    ],
    "sources": [
      "TREASURE"
    ]
  },
  {
    "id": "golem_muscle_enhancer",
    "name_kr": "GOLEM 근육 강화제",
    "grade": "B",
    "desc": "GOLEM 프로젝트 피실험체에게 투여하던 근육 증강제. 효과는 확실하다. 부작용은 몰라도.",
    "effects": [
      {
        "stat_key": "attack_power_flat",
        "label_kr": "공격력 (고정)",
        "value": 8.0,
        "mode": "add"
      },
      {
        "stat_key": "max_hp",
        "label_kr": "최대 체력",
        "value": 8.0,
        "mode": "add"
      }
    ],
    "sources": [
      "TREASURE"
    ]
  },
  {
    "id": "maglev_boots",
    "name_kr": "자기부상 부츠",
    "grade": "B",
    "desc": "KRONOS 차세대 기동 장비 프로토타입. 자기력으로 지면 반발력을 극대화한다.",
    "effects": [
      {
        "stat_key": "move_speed",
        "label_kr": "이동속도",
        "value": 7.0,
        "mode": "add"
      },
      {
        "stat_key": "jump_force",
        "label_kr": "점프력",
        "value": 7.0,
        "mode": "add"
      }
    ],
    "sources": [
      "TREASURE"
    ]
  },
  {
    "id": "flush_disruptor",
    "name_kr": "플러시 무력화 장치",
    "grade": "B",
    "desc": "하중 감지 센서의 임계값을 조작하는 장치. KRONOS 보안팀도 몰랐던 백도어를 이용한다.",
    "effects": [
      {
        "stat_key": "weight_limit_mult",
        "label_kr": "무게 한계 배율",
        "value": 0.2,
        "mode": "add"
      }
    ],
    "sources": [
      "TREASURE"
    ]
  },
  {
    "id": "aegis_core_chip",
    "name_kr": "AEGIS 코어 칩",
    "grade": "B",
    "desc": "AEGIS 로봇의 핵심 연산 칩. 고가 부품이라 KIOSK에서 높은 가격에 환전된다.",
    "effects": [
      {
        "stat_key": "robot_gold_mult",
        "label_kr": "로봇 처치 재화 배율",
        "value": 0.3,
        "mode": "add"
      }
    ],
    "sources": [
      "ROBOT_DROP"
    ]
  },
  {
    "id": "bio_reactive_suit",
    "name_kr": "생체 감응 수트",
    "grade": "B",
    "desc": "GOLEM 프로젝트 파생 기술로 만든 전투복. 위기 상황에서 착용자의 생체 반응을 극대화한다.",
    "effects": [],
    "sources": [
      "TREASURE"
    ]
  },
  {
    "id": "dual_structure_blueprint",
    "name_kr": "이중 구조 설계도",
    "grade": "B",
    "desc": "타워 07 이중 구조의 원본 설계도 일부. 어디를 파야 물자가 많은지 정확히 알 수 있다.",
    "effects": [
      {
        "stat_key": "mine_gold_mult",
        "label_kr": "벽 채굴 재화 배율",
        "value": 1.0,
        "mode": "add"
      }
    ],
    "sources": [
      "TREASURE"
    ]
  },
  {
    "id": "k00_combat_data_chip",
    "name_kr": "K-00 전투 데이터 칩",
    "grade": "A",
    "desc": "K-00의 전투 반응 데이터가 담긴 칩. 착용자의 신경계에 직접 접속해 전투 능력을 끌어올린다.",
    "effects": [
      {
        "stat_key": "attack_speed",
        "label_kr": "공격속도",
        "value": 15.0,
        "mode": "add"
      },
      {
        "stat_key": "attack_power_flat",
        "label_kr": "공격력 (고정)",
        "value": 10.0,
        "mode": "add"
      }
    ],
    "sources": [
      "TREASURE"
    ]
  },
  {
    "id": "golem_prototype_armor",
    "name_kr": "GOLEM 프로토타입 갑옷",
    "grade": "A",
    "desc": "GOLEM 피실험체용으로 제작된 외골격 갑옷. 방어력이 극도로 높지만 인간의 체형에 최적화되지 않았다.",
    "effects": [
      {
        "stat_key": "max_hp",
        "label_kr": "최대 체력",
        "value": 30.0,
        "mode": "add"
      },
      {
        "stat_key": "move_speed",
        "label_kr": "이동속도",
        "value": -5.0,
        "mode": "add"
      }
    ],
    "sources": [
      "TREASURE"
    ]
  },
  {
    "id": "nitrogen_barrier_suit",
    "name_kr": "질소 차단 수트",
    "grade": "A",
    "desc": "KRONOS 연구원들이 이중 구조 내부 작업 시 착용하던 특수 밀폐 수트.",
    "effects": [],
    "sources": [
      "TREASURE"
    ]
  },
  {
    "id": "flush_override_chip",
    "name_kr": "플러시 오버라이드 칩",
    "grade": "A",
    "desc": "플러시 프로토콜의 발동 임계값을 대폭 상향하는 관리자 권한 칩.",
    "effects": [
      {
        "stat_key": "weight_limit_mult",
        "label_kr": "무게 한계 배율",
        "value": 0.4,
        "mode": "add"
      }
    ],
    "sources": [
      "TREASURE"
    ]
  },
  {
    "id": "kronos_all_in_one",
    "name_kr": "KRONOS 만능 강화제",
    "grade": "A",
    "desc": "GOLEM 프로젝트의 최종 단계용으로 개발된 복합 강화제. 모든 능력치를 균형 있게 끌어올린다.",
    "effects": [
      {
        "stat_key": "max_hp",
        "label_kr": "최대 체력",
        "value": 10.0,
        "mode": "add"
      },
      {
        "stat_key": "attack_power_flat",
        "label_kr": "공격력 (고정)",
        "value": 5.0,
        "mode": "add"
      },
      {
        "stat_key": "move_speed",
        "label_kr": "이동속도",
        "value": 5.0,
        "mode": "add"
      },
      {
        "stat_key": "attack_speed",
        "label_kr": "공격속도",
        "value": 5.0,
        "mode": "add"
      }
    ],
    "sources": [
      "TREASURE"
    ]
  },
  {
    "id": "spring_boots",
    "name_kr": "용수철 장화",
    "grade": "S",
    "desc": "KRONOS 도시 탈출 훈련 장비. 단 한 번 더 도약할 수 있다는 것이 이 상황에서는 전부가 될 수 있다.",
    "effects": [],
    "sources": [
      "TREASURE"
    ]
  },
  {
    "id": "hypersonic_gauntlet",
    "name_kr": "초음속 장갑",
    "grade": "S",
    "desc": "GOLEM 프로젝트의 파생 병기. 착용 후 공격 속도가 인간의 한계를 넘어서지만, 신체 강화 약물 없이는 감당할 수 없다.",
    "effects": [
      {
        "stat_key": "attack_speed",
        "label_kr": "공격속도",
        "value": 50.0,
        "mode": "add"
      }
    ],
    "sources": [
      "TREASURE"
    ]
  },
  {
    "id": "golem_implant_chip",
    "name_kr": "GOLEM 이식 칩",
    "grade": "S",
    "desc": "K-00에게 이식됐던 생존 회로 칩. 착용자가 치명상을 입으면 자동으로 재기동 신호를 보낸다.",
    "effects": [],
    "sources": [
      "TREASURE"
    ]
  },
  {
    "id": "k00_memory",
    "name_kr": "K-00의 기억 조각",
    "grade": "S",
    "desc": "K-00이 마지막으로 저항했던 30초의 기록이 담긴 신경 칩. 그 의지가 프로토콜을 버텨낸다.",
    "effects": [],
    "sources": [
      "TREASURE"
    ]
  },
  {
    "id": "flush_override_code",
    "name_kr": "플러시 오버라이드 코드",
    "grade": "S",
    "desc": "플러시 프로토콜 자체를 무력화하는 최상위 관리자 코드. KRONOS CEO만이 가진 권한이었다. 대가는 있다.",
    "effects": [],
    "sources": [
      "TREASURE"
    ]
  },
  {
    "id": "test_one_handed_hammer",
    "name_kr": "한손 망치",
    "grade": "D",
    "item_type": "equipment",
    "equip_slot": "weapon",
    "desc": "[테스트] 기본 무기. 균형잡힌 성능.",
    "effects": [
      {
        "stat_key": "weapon_reach",
        "value": 48.0,
        "mode": "set",
        "label_kr": "사거리"
      },
      {
        "stat_key": "weapon_width",
        "value": 32.0,
        "mode": "set",
        "label_kr": "폭"
      },
      {
        "stat_key": "weapon_damage",
        "value": 12,
        "mode": "set",
        "label_kr": "데미지"
      },
      {
        "stat_key": "weapon_attack_speed",
        "value": 2.0,
        "mode": "set",
        "label_kr": "공격속도"
      },
      {
        "stat_key": "weapon_knockback",
        "value": 150.0,
        "mode": "set",
        "label_kr": "넉백"
      }
    ],
    "sources": [
      "KIOSK",
      "TREASURE"
    ]
  },
  {
    "id": "test_two_handed_hammer",
    "name_kr": "양손 망치",
    "grade": "B",
    "item_type": "equipment",
    "equip_slot": "weapon",
    "desc": "[테스트] 높은 데미지와 강한 넉백, 느린 공격속도.",
    "effects": [
      {
        "stat_key": "weapon_reach",
        "value": 64.0,
        "mode": "set",
        "label_kr": "사거리"
      },
      {
        "stat_key": "weapon_width",
        "value": 48.0,
        "mode": "set",
        "label_kr": "폭"
      },
      {
        "stat_key": "weapon_damage",
        "value": 28,
        "mode": "set",
        "label_kr": "데미지"
      },
      {
        "stat_key": "weapon_attack_speed",
        "value": 1.0,
        "mode": "set",
        "label_kr": "공격속도"
      },
      {
        "stat_key": "weapon_knockback",
        "value": 300.0,
        "mode": "set",
        "label_kr": "넉백"
      }
    ],
    "sources": [
      "KIOSK",
      "TREASURE"
    ]
  },
  {
    "id": "test_sword",
    "name_kr": "검",
    "grade": "C",
    "item_type": "equipment",
    "equip_slot": "weapon",
    "desc": "[테스트] 빠른 공격속도, 짧은 사거리, 약한 넉백.",
    "effects": [
      {
        "stat_key": "weapon_reach",
        "value": 40.0,
        "mode": "set",
        "label_kr": "사거리"
      },
      {
        "stat_key": "weapon_width",
        "value": 20.0,
        "mode": "set",
        "label_kr": "폭"
      },
      {
        "stat_key": "weapon_damage",
        "value": 7,
        "mode": "set",
        "label_kr": "데미지"
      },
      {
        "stat_key": "weapon_attack_speed",
        "value": 4.0,
        "mode": "set",
        "label_kr": "공격속도"
      },
      {
        "stat_key": "weapon_knockback",
        "value": 80.0,
        "mode": "set",
        "label_kr": "넉백"
      }
    ],
    "sources": [
      "KIOSK",
      "TREASURE"
    ]
  }
]